odoo/addons/stock_picking_report_custom_description/README.rst
odoo/addons/stock_picking_report_custom_description/__init__.py
odoo/addons/stock_picking_report_custom_description/__manifest__.py
odoo/addons/stock_picking_report_custom_description/i18n/es.po
odoo/addons/stock_picking_report_custom_description/i18n/it.po
odoo/addons/stock_picking_report_custom_description/i18n/stock_picking_report_custom_description.pot
odoo/addons/stock_picking_report_custom_description/models/__init__.py
odoo/addons/stock_picking_report_custom_description/models/sale_order_line.py
odoo/addons/stock_picking_report_custom_description/models/stock_rule.py
odoo/addons/stock_picking_report_custom_description/readme/CONTRIBUTORS.md
odoo/addons/stock_picking_report_custom_description/readme/DESCRIPTION.md
odoo/addons/stock_picking_report_custom_description/readme/USAGE.md
odoo/addons/stock_picking_report_custom_description/static/description/icon.png
odoo/addons/stock_picking_report_custom_description/static/description/index.html
odoo/addons/stock_picking_report_custom_description/tests/__init__.py
odoo/addons/stock_picking_report_custom_description/tests/test_stock_picking_report_custom_description.py
odoo_addon_stock_picking_report_custom_description-18.0.1.0.0.2.dist-info/METADATA
odoo_addon_stock_picking_report_custom_description-18.0.1.0.0.2.dist-info/WHEEL
odoo_addon_stock_picking_report_custom_description-18.0.1.0.0.2.dist-info/top_level.txt
odoo_addon_stock_picking_report_custom_description-18.0.1.0.0.2.dist-info/RECORD
